gym_sch/__init__.py
gym_sch/envs/__init__.py
gym_sch/envs/sch_env.py
gym_sch/envs/sim_py_v5.py
gym_sch/envs/sim_py_v6.py
gym_sch/envs/truck_schedule_v6.py
gym_sch-1.0.0.dist-info/METADATA
gym_sch-1.0.0.dist-info/RECORD
gym_sch-1.0.0.dist-info/WHEEL
gym_sch-1.0.0.dist-info/top_level.txt
