Metadata-Version: 2.1
Name: gym-sch
Version: 1.0.0
Summary: An OpenAI Gym Env for Pandas
Home-page: UNKNOWN
License: UNKNOWN
Platform: UNKNOWN
Requires-Dist: gym
